fetch_cpy_src/__init__.py
fetch_cpy_src/__main__.py
fetch_cpy_src/adapter.py
fetch_cpy_src/cli.py
fetch_cpy_src/downloader.py
fetch_cpy_src/example-manifest.toml
fetch_cpy_src/manifest.py
fetch_cpy_src/phy.toml
fetch_cpy_src-0.3.1.dist-info/METADATA
fetch_cpy_src-0.3.1.dist-info/WHEEL
fetch_cpy_src-0.3.1.dist-info/entry_points.txt
fetch_cpy_src-0.3.1.dist-info/licenses/LICENSE
fetch_cpy_src-0.3.1.dist-info/RECORD
