Metadata-Version: 2.4
Name: fetch-cpy-src
Version: 0.3.1
Summary: Fetch selected part of cpython source repository.
License: MIT
License-File: LICENSE
Author: Alfred DU
Author-email: ihearmywords@hotmail.com
Requires-Python: >=3.10, <4
Classifier: License :: OSI Approved :: MIT License
Classifier: Programming Language :: Python :: 3
Classifier: Programming Language :: Python :: 3.10
Classifier: Programming Language :: Python :: 3.11
Classifier: Programming Language :: Python :: 3.12
Classifier: Programming Language :: Python :: 3.13
Classifier: Programming Language :: Python :: 3.14
Requires-Dist: click (>=8.3.0,<9.0.0)
Requires-Dist: pygithub (>=2.6.1,<3.0.0)
Requires-Dist: requests (>=2.32.3,<3.0.0)
Requires-Dist: tomli (>=2.2.1,<3.0.0)
Project-URL: Documentation, https://fetch-cpy-src.readthedocs.io
Project-URL: Homepage, https://github.com/phy-precompiler/fetch-cpy-src
Project-URL: Issues, https://github.com/phy-precompiler/fetch-cpy-src/issues
Project-URL: Repository, https://github.com/phy-precompiler/fetch-cpy-src
